qioptiq_iris/__about__.py
qioptiq_iris/__init__.py
qioptiq_iris/lib.py
qioptiq_iris-0.0.1.dist-info/METADATA
qioptiq_iris-0.0.1.dist-info/WHEEL
qioptiq_iris-0.0.1.dist-info/licenses/LICENSE.txt
qioptiq_iris-0.0.1.dist-info/RECORD
