Metadata-Version: 2.4
Name: qioptiq-iris
Version: 0.0.1
Summary: Control for Qiotpiq iFLEX-iRIS laser.
Project-URL: Documentation, https://github.com/bicarlsen/qioptiq-iris#readme
Project-URL: Issues, https://github.com/bicarlsen/qioptiq-iris/issues
Project-URL: Source, https://github.com/bicarlsen/qioptiq-iris
Author-email: Brian Carlsen <carlsen.bri@gmail.com>
License-Expression: MIT
License-File: LICENSE.txt
Classifier: Development Status :: 4 - Beta
Classifier: Programming Language :: Python
Classifier: Programming Language :: Python :: 3.8
Classifier: Programming Language :: Python :: 3.9
Classifier: Programming Language :: Python :: 3.10
Classifier: Programming Language :: Python :: 3.11
Classifier: Programming Language :: Python :: 3.12
Classifier: Programming Language :: Python :: Implementation :: CPython
Classifier: Programming Language :: Python :: Implementation :: PyPy
Requires-Python: >=3.8
Requires-Dist: pyserial
Provides-Extra: dev
Requires-Dist: pytest; extra == 'dev'
